faber/__init__.py
faber/_version.py
faber/action.py
faber/artefact.py
faber/assembly.py
faber/builtin.py
faber/cache.py
faber/cli.py
faber/delayed.py
faber/error.py
faber/logging.py
faber/module.py
faber/output.py
faber/platform.py
faber/project.py
faber/rule.py
faber/termcolor.py
faber/tool.py
faber/types.py
faber/utils.py
faber/artefacts/__init__.py
faber/artefacts/binary.py
faber/artefacts/html.py
faber/artefacts/include_scan.py
faber/artefacts/inspect.py
faber/artefacts/install.py
faber/artefacts/library.py
faber/artefacts/object.py
faber/artefacts/python.py
faber/artefacts/boost/__init__.py
faber/artefacts/boost/test.py
faber/config/__init__.py
faber/config/c_checks.py
faber/config/check.py
faber/config/cxx_checks.py
faber/config/try_compile.py
faber/config/try_link.py
faber/config/try_run.py
faber/feature/__init__.py
faber/feature/condition.py
faber/feature/feature.py
faber/feature/map.py
faber/feature/set.py
faber/feature/value.py
faber/package/__init__.py
faber/package/archive.py
faber/package/manifest.py
faber/scheduler/__init__.py
faber/scheduler/artefact.py
faber/scheduler/asyncio.py
faber/scheduler/graph.py
faber/scheduler/recipe.py
faber/test/__init__.py
faber/test/report.py
faber/test/suite.py
faber/test/test.py
faber/tools/__init__.py
faber/tools/archiver.py
faber/tools/boost.py
faber/tools/cc.py
faber/tools/clang.py
faber/tools/clangxx.py
faber/tools/compiler.py
faber/tools/cxx.py
faber/tools/fileutils.py
faber/tools/gcc.py
faber/tools/gxx.py
faber/tools/installer.py
faber/tools/msvc.py
faber/tools/python.py
faber/tools/sphinx.py
faber/tools/xslt.py
faber-0.4.1.data/data/share/doc/faber-0.4.1/.buildinfo
faber-0.4.1.data/data/share/doc/faber-0.4.1/LICENSE
faber-0.4.1.data/data/share/doc/faber-0.4.1/README.md
faber-0.4.1.data/data/share/doc/faber-0.4.1/appendix.html
faber-0.4.1.data/data/share/doc/faber-0.4.1/cli.html
faber-0.4.1.data/data/share/doc/faber-0.4.1/genindex.html
faber-0.4.1.data/data/share/doc/faber-0.4.1/glossary.html
faber-0.4.1.dist-info/LICENSE
faber-0.4.1.dist-info/METADATA
faber-0.4.1.dist-info/WHEEL
faber-0.4.1.dist-info/entry_points.txt
faber-0.4.1.dist-info/top_level.txt
faber-0.4.1.dist-info/RECORD
